nostromo_cli/__init__.py
nostromo_cli/__main__.py
nostromo_cli/app.py
nostromo_cli/cli.py
nostromo_cli/config.py
nostromo_cli/history.py
nostromo_cli/secrets.py
nostromo_cli/styles/mother.tcss
nostromo_cli-0.1.0.dist-info/METADATA
nostromo_cli-0.1.0.dist-info/WHEEL
nostromo_cli-0.1.0.dist-info/entry_points.txt
nostromo_cli-0.1.0.dist-info/RECORD
